avi-okta/ApiClient.py
avi-okta/AviOktaClient.py
avi-okta/AviSendGridClient.py
avi-okta/OktaError.py
avi-okta/__init__.py
avi_okta/ApiClient.py
avi_okta/AviOktaClient.py
avi_okta/AviSendGridClient.py
avi_okta/OktaError.py
avi_okta/__init__.py
avi_okta-0.0.1.dist-info/METADATA
avi_okta-0.0.1.dist-info/RECORD
avi_okta-0.0.1.dist-info/WHEEL
avi_okta-0.0.1.dist-info/top_level.txt
