Metadata-Version: 2.1
Name: avi-okta
Version: 0.0.1
Summary: Avi Networks Okta sdk
Home-page: https://github.com/avinetworks/avi-internal
Author: Neel Parikh
Author-email: nparikh@avinetworks.com
License: UNKNOWN
Platform: UNKNOWN
Classifier: Programming Language :: Python :: 2
Classifier: Programming Language :: Python :: 2.6
Classifier: Programming Language :: Python :: 2.7
Classifier: License :: OSI Approved :: MIT License
Classifier: Operating System :: OS Independent
